Wrapper4AI/__init__.py
Wrapper4AI/base_handler.py
Wrapper4AI/config.py
Wrapper4AI/responder.py
Wrapper4AI/wrap.py
Wrapper4AI/handlers/__init__.py
Wrapper4AI/handlers/anthropic_handler.py
Wrapper4AI/handlers/bedrock_handler.py
Wrapper4AI/handlers/deepseek_handler.py
Wrapper4AI/handlers/gemini_handler.py
Wrapper4AI/handlers/hf_inference_handler.py
Wrapper4AI/handlers/huggingface_handler.py
Wrapper4AI/handlers/meta_llama_handler.py
Wrapper4AI/handlers/openai_handler.py
Wrapper4AI/handlers/perplexity_ai_handler.py
Wrapper4AI-0.1.2.dist-info/METADATA
Wrapper4AI-0.1.2.dist-info/WHEEL
Wrapper4AI-0.1.2.dist-info/top_level.txt
Wrapper4AI-0.1.2.dist-info/RECORD
