Metadata-Version: 2.2
Name: Wrapper4AI
Version: 0.1.2
Summary: A lightweight multi-provider wrapper for LLM chat with history and token management.
Home-page: https://github.com/DKethan/Wrapper4AI/tree/dev-01
Author: Kethan Dosapati
Requires-Python: >=3.7
Requires-Dist: openai
Requires-Dist: tiktoken
Requires-Dist: requests
Requires-Dist: huggingface_hub
Requires-Dist: boto3
Requires-Dist: anthropic
Dynamic: author
Dynamic: description
Dynamic: description-content-type
Dynamic: home-page
Dynamic: requires-dist
Dynamic: requires-python
Dynamic: summary
